{"cameraMode":{"drawMode":0,"name":"Shaded","section":"Shading Mode"},"sceneLighting":true,"audioPlay":false,"sceneViewState":{"m_AlwaysRefresh":false,"showFog":true,"showSkybox":true,"showFlares":true,"showImageEffects":true,"showParticleSystems":true,"showVisualEffectGraphs":true,"m_FxEnabled":true},"in2DMode":false,"pivot":{"x":14.586936950683594,"y":0.6129284501075745,"z":0.20443947613239289},"rotation":{"x":-0.14737969636917115,"y":0.6739313006401062,"z":-0.13947206735610963,"w":-0.7105114459991455},"size":1.1079269647598267,"orthographic":false}